bpylist2/__init__.py
bpylist2/_plistlib.py
bpylist2/archive_types.py
bpylist2/archiver.py
bpylist2-4.1.0.dist-info/WHEEL
bpylist2-4.1.0.dist-info/METADATA
bpylist2-4.1.0.dist-info/RECORD
