Metadata-Version: 2.1
Name: bpylist2
Version: 4.1.0
Summary: Parse and generate NSKeyedArchiver archives
License: MIT
Author: Jenia Varavva
Author-email: fuzzy.parabola@gmail.com
Requires-Python: >=3.7,<4.0
Classifier: License :: OSI Approved :: MIT License
Classifier: Programming Language :: Python :: 3
Classifier: Programming Language :: Python :: 3.7
Classifier: Programming Language :: Python :: 3.8
Classifier: Programming Language :: Python :: 3.9
Classifier: Programming Language :: Python :: 3.10
Classifier: Programming Language :: Python :: 3.11
Project-URL: homepage, https://github.com/parabolala/bpylist2
